frenchmaid/__init__.py
frenchmaid/__main__.py
frenchmaid/cli.py
frenchmaid/delcache.py
frenchmaid/modules/__init__.py
frenchmaid/modules/clean.py
frenchmaid/modules/ignore.py
frenchmaid/switches/__init__.py
frenchmaid/switches/cleanSwitch.py
frenchmaid/switches/ignoreSwitch.py
frenchmaid-0.2.3.dist-info/LICENSE
frenchmaid-0.2.3.dist-info/METADATA
frenchmaid-0.2.3.dist-info/WHEEL
frenchmaid-0.2.3.dist-info/entry_points.txt
frenchmaid-0.2.3.dist-info/top_level.txt
frenchmaid-0.2.3.dist-info/RECORD
