Metadata-Version: 2.1
Name: frenchmaid
Version: 0.2.3
Summary: Remove all pests from your project! frenchmaid is a lightweight all platform cli package that will delete all pycache and other folders (contents included) in your project directory. Are you tired of doing it manually each time? Fear not, the frenchmaid will do it for you!
Home-page: https://github.com/lewisjr/frenchmaid.git
Author: Cerebrus Inc | Lewis Mosho Jr
Author-email: lewis@cerebrus.dev
Project-URL: Bug Tracker, https://github.com/lewisjr/frenchmaid/issues
Classifier: License :: OSI Approved :: Apache Software License
Classifier: Programming Language :: Python :: 3
Classifier: Operating System :: OS Independent
Classifier: Topic :: Utilities
Classifier: Development Status :: 5 - Production/Stable
Classifier: Environment :: Console
Classifier: Intended Audience :: Developers
Classifier: Typing :: Typed
Requires-Python: >=3.0
License-File: LICENSE
Requires-Dist: click
Requires-Dist: colorama
Requires-Dist: typer
